pyqt_toast/__init__.py
pyqt_toast/toast.py
pyqt_toast/style/__init__.py
pyqt_toast/style/background.css
pyqt_toast/style/foreground.css
pyqt_toast-0.0.15.dist-info/LICENSE
pyqt_toast-0.0.15.dist-info/METADATA
pyqt_toast-0.0.15.dist-info/WHEEL
pyqt_toast-0.0.15.dist-info/top_level.txt
pyqt_toast-0.0.15.dist-info/RECORD
