Metadata-Version: 2.1
Name: pyqt-toast
Version: 0.0.15
Summary: PyQt Toast (Small message displayed on the screen, visible for a short time)
Home-page: https://github.com/yjg30737/pyqt-toast.git
Author: Jung Gyu Yoon
Author-email: yjg30737@gmail.com
License: MIT
License-File: LICENSE
Requires-Dist: PyQt5 (>=5.8)
Requires-Dist: pyqt-resource-helper (>=0.0.1)
